onboard/client/__init__.py
onboard/client/client.py
onboard/client/dataframes.py
onboard/client/exceptions.py
onboard/client/helpers.py
onboard/client/models.py
onboard/client/py.typed
onboard/client/staging.py
onboard/client/util.py
onboard_client-1.15.0.dist-info/LICENSE
onboard_client-1.15.0.dist-info/METADATA
onboard_client-1.15.0.dist-info/WHEEL
onboard_client-1.15.0.dist-info/top_level.txt
onboard_client-1.15.0.dist-info/RECORD
