Metadata-Version: 2.1
Name: onboard_client
Version: 1.15.0
Summary: Onboard API SDK
Home-page: https://github.com/onboard-data/client-py
Author: Nathan Merritt, John Vines
Author-email: support@onboarddata.io
Classifier: Development Status :: 5 - Production/Stable
Classifier: Environment :: Console
Classifier: Intended Audience :: Developers
Classifier: License :: OSI Approved :: Apache Software License
Classifier: Programming Language :: Python :: 3.8
Classifier: Programming Language :: Python :: 3.9
Classifier: Programming Language :: Python :: 3.10
Classifier: Programming Language :: Python :: 3.11
Classifier: Programming Language :: Python :: 3.12
Classifier: Programming Language :: Python :: 3.13
Classifier: Topic :: Scientific/Engineering :: Information Analysis
Classifier: Topic :: Software Development :: Libraries
Classifier: Topic :: Software Development :: Libraries :: Python Modules
Requires-Python: >=3.8
License-File: LICENSE
Requires-Dist: certifi >=2019.3.9
Requires-Dist: chardet >=3.0.4
Requires-Dist: idna >=2.8
Requires-Dist: requests >=2.21.0
Requires-Dist: urllib3 >=1.24.2
Requires-Dist: deprecation >=2.1.0
Requires-Dist: pydantic <4,>=2
Requires-Dist: orjson >=3.9.15
